Metadata-Version: 2.0
Name: odoo10-addon-l10n-es-toponyms
Version: 10.0.1.0.0
Summary: Topónimos españoles
Home-page: https://github.com/OCA/l10n-spain
Author: Spanish Localization Team, ZikZakMedia, Tecnativa, Odoo Community Association (OCA)
Author-email: support@odoo-community.org
License: AGPL-3
Platform: UNKNOWN
Requires-Dist: odoo (<10.1dev,>=10.0)
Requires-Dist: odoo10-addon-base-location-geonames-import
Classifier: Programming Language :: Python :: 2.7
Classifier: Framework :: Odoo
Classifier: License :: OSI Approved :: GNU Affero General Public License v3
